Metadata-Version: 1.0
Name: OpenQuant
Version: 0.0.3
Summary: futu openquant api
Home-page: https://github.com/FutunnOpen/OpenQuant
Author: futu
Author-email: ftdev@futunn.com
License: Apache License 2.0
Keywords: futu openquant api
Platform: UNKNOWN
